sspymgr/__init__.py
sspymgr/_plugin.py
sspymgr/configuration.py
sspymgr/dbsessions.py
sspymgr/globalfuncs.py
sspymgr/manager.py
sspymgr/models.py
sspymgr/path_helper.py
sspymgr/webgui.py
sspymgr/core/__init__.py
sspymgr/core/mail.py
sspymgr/core/routes.py
sspymgr/core/web_settings.py
sspymgr/core/web_user.py
sspymgr/locale/sspymgr.pot
sspymgr/locale/zh_CN/LC_MESSAGES/sspymgr.mo
sspymgr/locale/zh_CN/LC_MESSAGES/sspymgr.po
sspymgr/plugins/announcement.py
sspymgr/plugins/vuefront.py
sspymgr/plugins/web_order.py
sspymgr/plugins/ssextension/__init__.py
sspymgr/plugins/ssextension/flow_stats.py
sspymgr/plugins/ssextension/ssc_routes.py
sspymgr/sscontroller/__init__.py
sspymgr/sscontroller/adapter.py
sspymgr/sscontroller/database.py
sspymgr/sscontroller/run_ss.py
sspymgr/sscontroller/utils.py
sspymgr/vuetemplates/admin.html
sspymgr/vuetemplates/favicon.ico
sspymgr/vuetemplates/home.html
sspymgr/vuetemplates/user.html
sspymgr/vuetemplates/vstatic/css/admin.7cd697a4.css
sspymgr/vuetemplates/vstatic/css/chunk-37c01c16.94ee3d43.css
sspymgr/vuetemplates/vstatic/css/chunk-4029f52a.699b8860.css
sspymgr/vuetemplates/vstatic/css/chunk-482da312.53354840.css
sspymgr/vuetemplates/vstatic/css/chunk-4eb96bb6.383860bd.css
sspymgr/vuetemplates/vstatic/css/chunk-4f815c50.f243f417.css
sspymgr/vuetemplates/vstatic/css/chunk-563bbf29.ab9a3a4e.css
sspymgr/vuetemplates/vstatic/css/chunk-5d94552a.6a7632e7.css
sspymgr/vuetemplates/vstatic/css/chunk-5f4c2391.f367d627.css
sspymgr/vuetemplates/vstatic/css/chunk-6f54d604.894e22d4.css
sspymgr/vuetemplates/vstatic/css/chunk-89f27b9a.894e22d4.css
sspymgr/vuetemplates/vstatic/css/chunk-b333ca30.b4adec04.css
sspymgr/vuetemplates/vstatic/css/chunk-fb0413e0.91c18867.css
sspymgr/vuetemplates/vstatic/css/chunk-vendors.52dd4e00.css
sspymgr/vuetemplates/vstatic/css/home.d0c882e8.css
sspymgr/vuetemplates/vstatic/css/user.7cd697a4.css
sspymgr/vuetemplates/vstatic/fonts/fa-brands-400.50a544b5.ttf
sspymgr/vuetemplates/vstatic/fonts/fa-brands-400.7d43b9ae.eot
sspymgr-0.0.21.dist-info/LICENSE
sspymgr-0.0.21.dist-info/METADATA
sspymgr-0.0.21.dist-info/WHEEL
sspymgr-0.0.21.dist-info/entry_points.txt
sspymgr-0.0.21.dist-info/top_level.txt
sspymgr-0.0.21.dist-info/RECORD
