Metadata-Version: 2.1
Name: sspymgr
Version: 0.0.21
Summary: Web Manager for Shadowsocks Service, Python Version
Home-page: http://github.com/brifuture/minor-sspymgr
Author: BriFuture
Author-email: jw.brifuture@gmail.com
License: GPLv3
Keywords: webserver,shadowsocks-manager
Platform: UNKNOWN
Classifier: Programming Language :: Python
Classifier: Programming Language :: Python :: 3
Classifier: License :: OSI Approved :: GNU General Public License v3 (GPLv3)
Classifier: Operating System :: OS Independent
Requires-Dist: amqp (==2.3.2)
Requires-Dist: argh (==0.26.2)
Requires-Dist: billiard (==3.5.0.4)
Requires-Dist: celery (==4.2.1)
Requires-Dist: cffi (==1.11.5)
Requires-Dist: Click (==7.0)
Requires-Dist: Flask (==1.0.2)
Requires-Dist: Flask-Cors (==3.0.7)
Requires-Dist: Flask-SQLAlchemy (==2.3.2)
Requires-Dist: gevent (==1.3.7)
Requires-Dist: greenlet (==0.4.15)
Requires-Dist: itsdangerous (==0.24)
Requires-Dist: Jinja2 (==2.10)
Requires-Dist: kombu (==4.2.1)
Requires-Dist: MarkupSafe (==1.0)
Requires-Dist: pathtools (==0.1.2)
Requires-Dist: pycparser (==2.19)
Requires-Dist: pytz (==2018.6)
Requires-Dist: PyYAML (==3.13)
Requires-Dist: redis (==2.10.6)
Requires-Dist: schedule (==0.6.0)
Requires-Dist: shadowsocks-py (==2.9.1)
Requires-Dist: six (==1.11.0)
Requires-Dist: SQLAlchemy (==1.2.12)
Requires-Dist: vine (==1.1.4)
Requires-Dist: watchdog (==0.9.0)
Requires-Dist: Werkzeug (==0.14.1)
